Metadata-Version: 2.1
Name: cltl.vad
Version: 0.0.dev1
Summary: VAD for Leolani
Home-page: https://github.com/leolani/cltl-vad
Author: CLTL
Author-email: t.baier@vu.nl
License: MIT License
Platform: UNKNOWN
Requires-Python: >=3.7
Provides-Extra: impl
Provides-Extra: service
